[
  { "id": 998, "name": "Research Direct Consulting", "phone": "(828)463-9921" },
  { "id": 331, "name": "Solutions Software", "phone": "(707)371-2960" },
  { "id": 321, "name": "Direct Pacific", "phone": "(916)820-8813" },
  { "id": 554, "name": "Internet Building Studio", "phone": "(234)180-3788" },
  { "id": 224, "name": "Telecom Electronic", "phone": "(574)704-6905" },
  { "id": 962, "name": "Venture Technology", "phone": "(860)897-2229" },
  { "id": 987, "name": "Net Atlantic Internet", "phone": "(412)429-2598" },
  { "id": 510, "name": "Direct Star Solutions", "phone": "(878)529-3892" },
  { "id": 661, "name": "East Interactive", "phone": "(872)433-7282" },
  { "id": 242, "name": "Vision West", "phone": "(316)641-4311" },
  { "id": 925, "name": "Building Software Systems", "phone": "(832)138-1732" },
  { "id": 648, "name": "Power Construction Resource", "phone": "(865)982-6426" },
  { "id": 282, "name": "Signal Systems Virtual", "phone": "(570)211-4294" },
  { "id": 824, "name": "Internet Star Construction", "phone": "(557)971-2199" },
  { "id": 434, "name": "Medicine Data Analysis", "phone": "(916)649-3151" },
  { "id": 403, "name": "Internet Network", "phone": "(857)303-4619" },
  { "id": 327, "name": "Analysis Digital Adventure", "phone": "(702)290-6633" },
  { "id": 562, "name": "Federated Virtual Design", "phone": "(757)421-7333" },
  { "id": 759, "name": "Innovation Electronic Pacific", "phone": "(484)561-4328" },
  { "id": 365, "name": "Technology Federated Alpha", "phone": "(412)606-5052" },
  { "id": 826, "name": "Speed People Consulting", "phone": "(802)800-3250" },
  { "id": 89, "name": "Net Software", "phone": "(515)192-1226" },
  { "id": 763, "name": "Universal Vision Speed", "phone": "(219)213-3780" },
  { "id": 605, "name": "Telecom Universal Alpha", "phone": "(260)278-9590" },
  { "id": 144, "name": "East People Universal", "phone": "(859)674-4220" },
  { "id": 76, "name": "Architecture Alpha Interactive", "phone": "(606)680-6533" },
  { "id": 220, "name": "Internet Innovation Speed", "phone": "(316)293-2420" },
  { "id": 146, "name": "Technology Federated Pacific", "phone": "(606)467-3964" },
  { "id": 566, "name": "Pacific Industries Star", "phone": "(208)652-3815" },
  { "id": 900, "name": "Medicine Consulting", "phone": "(605)137-3868" },
  { "id": 745, "name": "General Innovation Electronic", "phone": "(832)506-3506" },
  { "id": 961, "name": "Industries South", "phone": "(835)131-8684" },
  { "id": 596, "name": "Federated Digital", "phone": "(913)700-5141" },
  { "id": 87, "name": "Net Building", "phone": "(872)938-8248" },
  { "id": 805, "name": "Bell Alpha Architecture", "phone": "(702)282-8038" },
  { "id": 525, "name": "Network Vision", "phone": "(281)743-2423" },
  { "id": 473, "name": "Medicine Systems Universal", "phone": "(303)881-2842" },
  { "id": 2, "name": "Technology Consulting Systems", "phone": "(251)838-4546" },
  { "id": 438, "name": "Universal Software", "phone": "(262)583-3224" },
  { "id": 463, "name": "Universal West", "phone": "(662)233-8811" },
  { "id": 608, "name": "Source Star", "phone": "(571)485-3793" },
  { "id": 181, "name": "Adventure Application Construction", "phone": "(804)144-7015" },
  { "id": 901, "name": "West Omega Star", "phone": "(404)923-7133" },
  { "id": 804, "name": "Provider Architecture Interactive", "phone": "(269)920-8625" },
  { "id": 245, "name": "Pacific Electronics Hardware", "phone": "(631)484-2338" },
  { "id": 47, "name": "Vision Analysis", "phone": "(505)710-8949" },
  { "id": 706, "name": "Solutions Net Adventure", "phone": "(435)625-5577" },
  { "id": 720, "name": "Adventure Alpha Graphics", "phone": "(907)889-2358" },
  { "id": 791, "name": "Hardware Omega Consulting", "phone": "(601)758-8538" },
  { "id": 725, "name": "Studio Future", "phone": "(424)318-4675" },
  { "id": 781, "name": "Bell Atlantic", "phone": "(469)954-6734" },
  { "id": 873, "name": "Innovation Contract Analysis", "phone": "(802)532-7690" },
  { "id": 4, "name": "Application Contract Advanced", "phone": "(406)534-5120" },
  { "id": 522, "name": "Industries West Omega", "phone": "(801)195-7171" },
  { "id": 656, "name": "Bell Electronic", "phone": "(603)747-3393" },
  { "id": 868, "name": "Resource Advanced Construction", "phone": "(352)789-9207" },
  { "id": 406, "name": "Digital Atlantic Software", "phone": "(917)685-3855" },
  { "id": 339, "name": "South Medicine Omega", "phone": "(607)408-6063" },
  { "id": 515, "name": "Data Solutions Design", "phone": "(610)770-3141" },
  { "id": 984, "name": "Building Signal", "phone": "(660)520-7651" },
  { "id": 500, "name": "Galaxy Direct Technology", "phone": "(260)549-2883" },
  { "id": 494, "name": "Venture Internet", "phone": "(775)860-1700" },
  { "id": 637, "name": "Innovation Analysis Power", "phone": "(510)181-9660" },
  { "id": 750, "name": "South Construction Hardware", "phone": "(434)358-7916" },
  { "id": 246, "name": "Telecom Studio Alpha", "phone": "(470)908-5993" },
  { "id": 972, "name": "Industries Electronic", "phone": "(419)624-5674" },
  { "id": 717, "name": "Star Hardware", "phone": "(601)669-6081" },
  { "id": 208, "name": "Building South Analysis", "phone": "(975)195-5320" },
  { "id": 3, "name": "Pacific Digital People", "phone": "(979)577-7122" },
  { "id": 229, "name": "Vision Virtual", "phone": "(405)682-6745" },
  { "id": 789, "name": "General Medicine Vision", "phone": "(606)854-5926" },
  { "id": 797, "name": "North Consulting", "phone": "(715)355-1172" },
  { "id": 670, "name": "Net Electronic Digital", "phone": "(920)493-5168" },
  { "id": 415, "name": "Data General Advanced", "phone": "(440)963-6544" },
  { "id": 325, "name": "Data Architecture Future", "phone": "(312)438-7277" },
  { "id": 703, "name": "Industries Contract", "phone": "(707)291-9294" },
  { "id": 131, "name": "Alpha Star Telecom", "phone": "(317)537-7402" },
  { "id": 315, "name": "West Electronic", "phone": "(283)926-8331" },
  { "id": 472, "name": "Innovation Source", "phone": "(228)601-7359" },
  { "id": 491, "name": "Architecture Telecom Systems", "phone": "(872)631-9332" },
  { "id": 57, "name": "Innovation Digital", "phone": "(303)709-7134" },
  { "id": 335, "name": "Studio Interactive Industries", "phone": "(503)445-8910" },
  { "id": 669, "name": "Medicine Telecom", "phone": "(910)827-4294" },
  { "id": 279, "name": "Speed Application Electronics", "phone": "(719)115-2496" },
  { "id": 56, "name": "Frontier Consulting Digital", "phone": "(503)409-1164" },
  { "id": 397, "name": "Signal Resource General", "phone": "(559)650-2445" },
  { "id": 593, "name": "Interactive Max", "phone": "(954)589-1382" },
  { "id": 353, "name": "Star Max Bell", "phone": "(206)424-8808" },
  { "id": 255, "name": "Industries Interactive", "phone": "(802)570-9213" },
  { "id": 908, "name": "People Telecom East", "phone": "(207)663-5888" },
  { "id": 337, "name": "Venture Vision", "phone": "(940)929-5508" },
  { "id": 419, "name": "Frontier Interactive Graphics", "phone": "(351)385-3416" },
  { "id": 580, "name": "Atlantic Advanced", "phone": "(229)605-4822" },
  { "id": 794, "name": "Source Resource Innovation", "phone": "(505)736-3834" },
  { "id": 124, "name": "Solutions Hill", "phone": "(580)875-4627" },
  { "id": 753, "name": "East Pacific", "phone": "(630)413-3792" },
  { "id": 665, "name": "Direct Speed Telecom", "phone": "(312)284-4538" },
  { "id": 81, "name": "Systems Frontier", "phone": "(701)816-8578" },
  { "id": 626, "name": "Research People Virtual", "phone": "(717)115-6058" },
  { "id": 152, "name": "Pacific People Software", "phone": "(864)687-7818" },
  { "id": 338, "name": "Internet Speed East", "phone": "(564)900-8703" },
  { "id": 702, "name": "Galaxy Studio Universal", "phone": "(406)376-6188" },
  { "id": 577, "name": "Systems Design Resource", "phone": "(804)931-6246" },
  { "id": 780, "name": "Star Venture Software", "phone": "(920)223-4951" },
  { "id": 165, "name": "Atlantic Virtual", "phone": "(806)723-4182" },
  { "id": 913, "name": "Design Power Net", "phone": "(213)355-8073" },
  { "id": 486, "name": "Direct Graphics", "phone": "(423)551-2249" },
  { "id": 904, "name": "Electronic Network", "phone": "(620)475-3667" },
  { "id": 254, "name": "Virtual Industries Hardware", "phone": "(504)473-7400" },
  { "id": 951, "name": "Building Research Data", "phone": "(269)394-8848" },
  { "id": 265, "name": "Hardware Construction", "phone": "(959)578-4951" },
  { "id": 589, "name": "Bell Data", "phone": "(425)429-8578" },
  { "id": 44, "name": "People Universal", "phone": "(816)828-4756" },
  { "id": 82, "name": "Bell General Solutions", "phone": "(419)954-3132" },
  { "id": 191, "name": "Vision West", "phone": "(845)907-2554" },
  { "id": 561, "name": "Source Direct Innovation", "phone": "(859)701-8087" },
  { "id": 417, "name": "Venture Net", "phone": "(317)353-7327" },
  { "id": 642, "name": "Building Power Speed", "phone": "(617)905-5025" },
  { "id": 8, "name": "Atlantic Virtual Star", "phone": "(557)211-9567" },
  { "id": 559, "name": "Technology People North", "phone": "(507)435-8157" },
  { "id": 71, "name": "Electronics Direct Frontier", "phone": "(618)525-8014" },
  { "id": 91, "name": "Electronic Electronics Systems", "phone": "(208)283-4385" },
  { "id": 363, "name": "Federated Adventure", "phone": "(865)269-4806" },
  { "id": 597, "name": "East North Electronics", "phone": "(606)790-6042" },
  { "id": 550, "name": "Studio Star Analysis", "phone": "(208)657-9458" },
  { "id": 350, "name": "Interactive Pacific Consulting", "phone": "(540)559-4431" },
  { "id": 594, "name": "Contract Speed", "phone": "(918)187-4773" },
  { "id": 105, "name": "Pacific Frontier People", "phone": "(484)651-2128" },
  { "id": 988, "name": "Direct Universal Studio", "phone": "(831)654-9984" },
  { "id": 644, "name": "Advanced Future South", "phone": "(682)114-4119" },
  { "id": 936, "name": "Digital Systems Innovation", "phone": "(304)388-4339" },
  { "id": 200, "name": "Research Solutions Alpha", "phone": "(336)796-6876" },
  { "id": 160, "name": "Bell Design Interactive", "phone": "(315)662-2977" },
  { "id": 898, "name": "Systems Federated Net", "phone": "(914)366-1572" },
  { "id": 349, "name": "Omega Electronics Telecom", "phone": "(702)661-1777" },
  { "id": 624, "name": "North Medicine Design", "phone": "(407)321-2807" },
  { "id": 935, "name": "Solutions Design", "phone": "(815)835-7668" },
  { "id": 462, "name": "Data Vision", "phone": "(805)777-9267" },
  { "id": 409, "name": "Technology Star Building", "phone": "(347)601-9225" },
  { "id": 865, "name": "Bell Interactive Max", "phone": "(443)723-7557" },
  { "id": 75, "name": "Alpha Bell Signal", "phone": "(785)462-9338" },
  { "id": 408, "name": "Bell People Adventure", "phone": "(607)782-8344" },
  { "id": 996, "name": "Technology Advanced", "phone": "(334)403-6945" },
  { "id": 527, "name": "Source Federated Advanced", "phone": "(201)377-9757" },
  { "id": 213, "name": "West Graphics Telecom", "phone": "(609)596-4748" },
  { "id": 736, "name": "North West Virtual", "phone": "(203)506-6267" },
  { "id": 480, "name": "Universal Provider Adventure", "phone": "(773)305-4710" },
  { "id": 675, "name": "Venture Galaxy South", "phone": "(212)855-8915" },
  { "id": 705, "name": "West Solutions Speed", "phone": "(959)128-3134" },
  { "id": 541, "name": "Net Electronic Vision", "phone": "(303)545-3272" },
  { "id": 786, "name": "Pacific Design Star", "phone": "(414)826-7597" },
  { "id": 646, "name": "Technology Star East", "phone": "(260)795-7574" },
  { "id": 13, "name": "Innovation Vision", "phone": "(570)384-7672" },
  { "id": 132, "name": "Omega Resource", "phone": "(928)199-2660" },
  { "id": 197, "name": "Electronics Network Venture", "phone": "(605)224-3947" },
  { "id": 109, "name": "Adventure Star South", "phone": "(219)267-2178" },
  { "id": 966, "name": "Direct Vision", "phone": "(919)948-6599" },
  { "id": 830, "name": "Universal North Electronics", "phone": "(603)655-3400" },
  { "id": 599, "name": "Contract Provider Frontier", "phone": "(912)214-3174" },
  { "id": 905, "name": "Innovation People Interactive", "phone": "(620)777-3473" },
  { "id": 999, "name": "Electronic South", "phone": "(727)288-8174" },
  { "id": 50, "name": "Digital Construction", "phone": "(714)349-8470" },
  { "id": 23, "name": "Architecture Contract Venture", "phone": "(253)269-5015" },
  { "id": 521, "name": "Contract West", "phone": "(276)122-4129" },
  { "id": 303, "name": "Frontier Technology Star", "phone": "(214)641-2120" },
  { "id": 66, "name": "Vision Industries Software", "phone": "(567)111-2802" },
  { "id": 235, "name": "West Direct Digital", "phone": "(754)500-3020" },
  { "id": 840, "name": "Virtual Solutions Bell", "phone": "(312)594-5967" },
  { "id": 370, "name": "Construction South", "phone": "(910)591-5606" },
  { "id": 62, "name": "East Research South", "phone": "(815)959-8662" },
  { "id": 713, "name": "Systems Source Network", "phone": "(682)594-7603" },
  { "id": 190, "name": "Electronic Innovation", "phone": "(737)447-4384" },
  { "id": 832, "name": "Future Advanced Pacific", "phone": "(828)148-3306" },
  { "id": 723, "name": "Industries Network", "phone": "(219)239-7982" },
  { "id": 989, "name": "Max Solutions Speed", "phone": "(319)636-7371" },
  { "id": 742, "name": "People Venture", "phone": "(701)295-5557" },
  { "id": 428, "name": "Hardware Digital", "phone": "(530)472-8169" },
  { "id": 187, "name": "Resource Industries East", "phone": "(334)186-6405" },
  { "id": 639, "name": "Electronics Graphics Systems", "phone": "(210)730-2440" },
  { "id": 834, "name": "Construction Graphics", "phone": "(843)460-1761" },
  { "id": 964, "name": "Net Net", "phone": "(860)815-8814" },
  { "id": 458, "name": "Vision Bell Provider", "phone": "(314)236-7376" },
  { "id": 737, "name": "Net Construction Virtual", "phone": "(606)669-4246" },
  { "id": 297, "name": "West Electronic Resource", "phone": "(412)702-9588" },
  { "id": 768, "name": "Digital Future", "phone": "(830)433-3547" },
  { "id": 68, "name": "Analysis Advanced", "phone": "(602)146-8803" },
  { "id": 452, "name": "East Digital", "phone": "(571)403-9402" },
  { "id": 748, "name": "Frontier Telecom Research", "phone": "(919)214-8789" },
  { "id": 847, "name": "Internet Telecom Consulting", "phone": "(541)353-6819" },
  { "id": 59, "name": "Federated Star Electronic", "phone": "(835)815-4617" },
  { "id": 115, "name": "Frontier Interactive", "phone": "(603)783-8904" },
  { "id": 618, "name": "Future Research Contract", "phone": "(508)615-1305" },
  { "id": 399, "name": "Graphics Signal", "phone": "(304)292-3631" },
  { "id": 844, "name": "Telecom Max Future", "phone": "(260)203-4353" },
  { "id": 683, "name": "Digital South", "phone": "(701)909-3401" },
  { "id": 709, "name": "West Architecture Graphics", "phone": "(912)883-7946" },
  { "id": 46, "name": "North Graphics", "phone": "(419)285-7573" },
  { "id": 814, "name": "Consulting Design West", "phone": "(715)270-8890" },
  { "id": 602, "name": "Technology Medicine Net", "phone": "(567)367-2588" },
  { "id": 604, "name": "Net Future Construction", "phone": "(701)339-8892" }
]
